jdiff/__init__.py
jdiff/check_types.py
jdiff/evaluators.py
jdiff/extract_data.py
jdiff/operator.py
jdiff/utils/__init__.py
jdiff/utils/data_normalization.py
jdiff/utils/diff_helpers.py
jdiff/utils/jmespath_parsers.py
jdiff-1.0.1.dist-info/LICENSE
jdiff-1.0.1.dist-info/METADATA
jdiff-1.0.1.dist-info/WHEEL
jdiff-1.0.1.dist-info/RECORD
