Metadata-Version: 2.3
Name: jdiff
Version: 1.0.1
Summary: A light-weight library to compare structured output from network devices show commands.
License: Apache-2.0
Keywords: json,diff,network
Author: Network to Code, LLC
Author-email: info@networktocode.com
Requires-Python: >=3.9,<4.0
Classifier: Development Status :: 5 - Production/Stable
Classifier: Intended Audience :: Developers
Classifier: License :: OSI Approved :: Apache Software License
Classifier: Programming Language :: Python :: 3
Classifier: Programming Language :: Python :: 3.9
Classifier: Programming Language :: Python :: 3.10
Classifier: Programming Language :: Python :: 3.11
Classifier: Programming Language :: Python :: 3.12
Classifier: Programming Language :: Python :: 3.13
Requires-Dist: deepdiff (>=8.6.1,<9.0.0)
Requires-Dist: jmespath (>=1.0.1,<2.0.0)
Project-URL: Documentation, https://jdiff.readthedocs.io
Project-URL: Homepage, https://jdiff.readthedocs.io
Project-URL: Repository, https://github.com/networktocode/jdiff
